detect_app/__init__.py
detect_app-0.0.5.dist-info/LICENSE
detect_app-0.0.5.dist-info/METADATA
detect_app-0.0.5.dist-info/WHEEL
detect_app-0.0.5.dist-info/top_level.txt
detect_app-0.0.5.dist-info/RECORD
