Metadata-Version: 2.2
Name: detect-app
Version: 0.0.5
Summary: detect which app the python interpreter is running in
Author: Hannes
Project-URL: Homepage, https://github.com/hannesdelbeke/detect-app
Keywords: dcc,app,application,pipeline
Classifier: Programming Language :: Python :: 3.7
Requires-Python: >=3.4
License-File: LICENSE
Requires-Dist: importlib-metadata; python_version < "3.7"
